syria/__init__.py
syria-0.1.dist-info/METADATA
syria-0.1.dist-info/WHEEL
syria-0.1.dist-info/top_level.txt
syria-0.1.dist-info/RECORD
