Metadata-Version: 2.1
Name: syria
Version: 0.1
Summary: Free syria for ever.
Author-email: ZAID <y8838@hotmail.com>
